<?xml version="1.0" encoding="UTF-8"?>
<objects serializationModel="Studio.02.02.00">
	<object class="AudioFile" id="{8503c667-a0a1-4511-95b2-a6a3c19ae30d}">
		<property name="assetPath">
			<value>sfx/sfx_cottongone.wav</value>
		</property>
		<property name="frequencyInKHz">
			<value>48</value>
		</property>
		<property name="channelCount">
			<value>2</value>
		</property>
		<property name="length">
			<value>2.4801458333333333</value>
		</property>
		<relationship name="masterAssetFolder">
			<destination>{c7fb5ed7-ebf7-498e-89a3-af0ad096eb3a}</destination>
		</relationship>
	</object>
</objects>
