<?xml version="1.0" encoding="UTF-8"?>
<objects serializationModel="Studio.02.02.00">
	<object class="AudioFile" id="{a970764f-188a-48d9-beaa-3fa49283049f}">
		<property name="assetPath">
			<value>SFX/flickflying.wav</value>
		</property>
		<property name="frequencyInKHz">
			<value>48</value>
		</property>
		<property name="channelCount">
			<value>2</value>
		</property>
		<property name="length">
			<value>5.7483124999999999</value>
		</property>
		<relationship name="masterAssetFolder">
			<destination>{c7fb5ed7-ebf7-498e-89a3-af0ad096eb3a}</destination>
		</relationship>
	</object>
</objects>
